docker_ipsec/__init__.py
docker_ipsec/common.py
docker_ipsec/docker-ipsec.py
docker_ipsec-0.3.data/scripts/docker-ipsec.py
docker_ipsec-0.3.dist-info/DESCRIPTION.rst
docker_ipsec-0.3.dist-info/METADATA
docker_ipsec-0.3.dist-info/RECORD
docker_ipsec-0.3.dist-info/WHEEL
docker_ipsec-0.3.dist-info/metadata.json
docker_ipsec-0.3.dist-info/top_level.txt
