Metadata-Version: 2.0
Name: docker-ipsec
Version: 0.3
Summary: Scripts to start/stop ipsec VPN tunnels while adding/removing iptables rules for docker networking.
Home-page: https://github.com/cbrichford/docker-ipsec/
Author: Christopher Brichford
Author-email: chrisb@farmersbusinessnetwork.com
License: Apache License 2.0
Keywords: ipsec,docker
Platform: UNKNOWN
Classifier: Development Status :: 3 - Alpha
Classifier: Environment :: Console
Classifier: Intended Audience :: Information Technology
Classifier: License :: OSI Approved :: Apache Software License
Classifier: Operating System :: POSIX :: Linux
Classifier: Topic :: Internet
Classifier: Topic :: System :: Networking
Requires-Dist: ipsecparse
Requires-Dist: netaddr
Requires-Dist: pyroute2
Requires-Dist: python-iptables
